libmc/__init__.py
libmc/_client.cpython-38-darwin.so
libmc-1.4.14.dist-info/RECORD
libmc-1.4.14.dist-info/WHEEL
libmc-1.4.14.dist-info/top_level.txt
libmc-1.4.14.dist-info/LICENSE.txt
libmc-1.4.14.dist-info/METADATA
