Metadata-Version: 2.1
Name: libmc
Version: 1.4.14
Summary: Fast and light-weight memcached client for C++/Python
Home-page: https://github.com/douban/libmc
Author: PAN, Myautsai
Author-email: myautsai@gmail.com
License: BSD License
Keywords: memcached,memcache,client
Classifier: Programming Language :: C++
Classifier: Programming Language :: Python
Classifier: Programming Language :: Python :: 3
Classifier: Programming Language :: Python :: 3.10
Classifier: Programming Language :: Python :: 3.11
Classifier: Programming Language :: Python :: 3.12
Classifier: Programming Language :: Python :: 3.13
Classifier: Programming Language :: Python :: 3.14
Classifier: Programming Language :: Python :: Implementation :: CPython
Classifier: Development Status :: 5 - Production/Stable
Classifier: Operating System :: POSIX :: Linux
Classifier: Intended Audience :: Developers
Classifier: License :: OSI Approved :: BSD License
Classifier: Topic :: Software Development :: Libraries
License-File: LICENSE.txt
